synapse_downloader/__init__.py
synapse_downloader/_version.py
synapse_downloader/cli.py
synapse_downloader/commands/__init__.py
synapse_downloader/commands/download/__init__.py
synapse_downloader/commands/download/cli.py
synapse_downloader/commands/download/downloader.py
synapse_downloader/commands/sync_from_synapse/__init__.py
synapse_downloader/commands/sync_from_synapse/cli.py
synapse_downloader/commands/sync_from_synapse/sync_from_synapse.py
synapse_downloader/core/__init__.py
synapse_downloader/core/env.py
synapse_downloader/core/exceptions.py
synapse_downloader/core/synapse_item.py
synapse_downloader/core/utils.py
synapse_downloader-0.2.0.dist-info/LICENSE
synapse_downloader-0.2.0.dist-info/METADATA
synapse_downloader-0.2.0.dist-info/NOTICE
synapse_downloader-0.2.0.dist-info/WHEEL
synapse_downloader-0.2.0.dist-info/entry_points.txt
synapse_downloader-0.2.0.dist-info/top_level.txt
synapse_downloader-0.2.0.dist-info/RECORD
