Metadata-Version: 2.1
Name: synapse-downloader
Version: 0.2.0
Summary: Utility for downloading large datasets from Synapse.
Home-page: https://github.com/ki-tools/synapse-downloader
License: Apache2
Classifier: Programming Language :: Python
Classifier: Programming Language :: Python :: 3.10
Classifier: Programming Language :: Python :: 3.11
Classifier: License :: OSI Approved :: Apache Software License
Classifier: Operating System :: OS Independent
License-File: LICENSE
License-File: NOTICE
Requires-Dist: synapseclient <3.0.0,>=2.3.1
Requires-Dist: synapsis >=0.0.7
